{
  "Easy": {
    "Q1": "Retrieve all data from the `customers` table.",
    "Q2": "Get the `productname` and `price` of all products.",
    "Q3": "Find all products with a `price` greater than $100.",
    "Q4": "Find all customers who live in 'New York'.",
    "Q5": "Find all orders with a 'Pending' status.",
    "Q6": "Find all products where the `productname` includes the word 'Laptop'.",
    "Q7": "Find all customers who joined the platform in the year 2023.",
    "Q8": "Find all products belonging to `categoryid` 1 or 2.",
    "Q9": "Find all products with a `stockquantity` between 20 and 50.",
    "Q10": "Retrieve all unique cities where customers are located."
  },
  "Medium": {
    "Q11": "Count the total number of customers.",
    "Q12": "Find the average price of all products.",
    "Q13": "Find the total `stockquantity` of all products combined.",
    "Q14": "Find the `orderdate` of the earliest (oldest) order.",
    "Q15": "Find the `orderdate` of the latest (most recent) order.",
    "Q16": "Get the number of products in each `categoryid`.",
    "Q17": "Get the total number of orders placed by each `customerid`.",
    "Q18": "Get the total value (`quantity` * `unitprice`) for `orderid` 101.",
    "Q19": "List all `productname` and their corresponding `categoryname`.",
    "Q20": "List all orders (orderid) and the `firstname` of the customer who placed them.",
    "Q21": "Find the total number of items (sum of `quantity`) sold for each `productid`.",
    "Q22": "Find all customers who have *not* placed any orders.",
    "Q23": "List all products (productid) that have *never* been sold.",
    "Q24": "Find the most expensive product (`price`).",
    "Q25": "List all customers, ordered by their `joindate` from newest to oldest."
  },
  "Hard": {
    "Q26": "Calculate the total revenue (sum of `quantity` * `unitprice`) for each order.",
    "Q27": "Find the names of customers who have spent more than $1,000 in total.",
    "Q28": "Find the `productname` and `price` of products that cost more than the average price of all products.",
    "Q29": "List all categories that have more than 10 products.",
    "Q30": "Find the total sales revenue generated by each `categoryname`.",
    "Q31": "Find the `customerid` and the total number of *unique* products they have purchased.",
    "Q32": "Find the top 5 best-selling products (by total `quantity` sold).",
    "Q33": "Find the customer (`firstname`, `lastname`) who placed the most recent order.",
    "Q34": "List all products that were sold in orders placed in January 2024.",
    "Q35": "Find the average order value (total revenue / total number of orders).",
    "Q36": "List customers who have placed 5 or more orders.",
    "Q37": "Find the total revenue generated in the month of March 2023.",
    "Q38": "Find customers who have bought 'Product A' (e.g., `productid` 5).",
    "Q39": "Find the `productname` of the product with the highest `stockquantity`.",
    "Q40": "Calculate the average `quantity` of products per order."
  },
  "Complicated": {
    "Q41": "Find customers whose average order value is higher than the overall average order value for all customers.",
    "Q42": "List the categories where the average product price is higher than the overall average product price across all categories.",
    "Q43": "Find the top 3 customers (by total spending) in each `city`.",
    "Q44": "Calculate the running total of revenue for each day in December 2023.",
    "Q45": "Find the time (in days) between a customer's first and second order.",
    "Q46": "Find customers who bought 'Product A' AND 'Product B'.",
    "Q47": "Find customers who bought 'Product A' but NOT 'Product B'.",
    "Q48": "Calculate the percentage of total sales revenue that each `categoryname` represents.",
    "Q49": "Find the product (or products) that appears in the most *different* orders.",
    "Q50": "For each customer, find their total spending and the total spending of the customer who joined just *before* them.",
    "Q51": "Find all orders that contain more than 5 *different* products.",
    "Q52": "Calculate the 3-day moving average of total sales revenue."
  }
}